{
    "l0": [
        {
            "index": 0,
            "x": 11,
            "y": -10
        },
        {
            "index": 1,
            "x": 11,
            "y": -9
        },
        {
            "index": 2,
            "x": 11,
            "y": -8
        },
        {
            "index": 3,
            "x": 11,
            "y": -7
        },
        {
            "index": 4,
            "x": 10,
            "y": -7
        },
        {
            "index": 5,
            "x": 9,
            "y": -7
        },
        {
            "index": 6,
            "x": 8,
            "y": -7
        },
        {
            "index": 7,
            "x": 7,
            "y": -7
        },
        {
            "index": 8,
            "x": 6,
            "y": -7
        },
        {
            "index": 9,
            "x": 5,
            "y": -7
        },
        {
            "index": 10,
            "x": 4,
            "y": -7
        },
        {
            "index": 11,
            "x": 4,
            "y": -8
        },
        {
            "index": 12,
            "x": 4,
            "y": -9
        },
        {
            "index": 13,
            "x": 4,
            "y": -10
        }
    ],
    "l1": [
        {
            "index": 0,
            "x": 3,
            "y": -7
        },
        {
            "index": 1,
            "x": 4,
            "y": -7
        },
        {
            "index": 2,
            "x": 5,
            "y": -7
        },
        {
            "index": 3,
            "x": 6,
            "y": -7
        },
        {
            "index": 4,
            "x": 7,
            "y": -7
        },
        {
            "index": 5,
            "x": 7,
            "y": -8
        },
        {
            "index": 6,
            "x": 7,
            "y": -9
        },
        {
            "index": 7,
            "x": 7,
            "y": -10
        }
    ],
    "l2": [],
    "l3": [
        {
            "index": 0,
            "x": 12,
            "y": -5
        },
        {
            "index": 1,
            "x": 11,
            "y": -5
        },
        {
            "index": 2,
            "x": 10,
            "y": -5
        },
        {
            "index": 3,
            "x": 9,
            "y": -5
        },
        {
            "index": 4,
            "x": 8,
            "y": -5
        },
        {
            "index": 5,
            "x": 8,
            "y": -4
        },
        {
            "index": 6,
            "x": 8,
            "y": -3
        },
        {
            "index": 7,
            "x": 8,
            "y": -2
        },
        {
            "index": 8,
            "x": 8,
            "y": -1
        },
        {
            "index": 9,
            "x": 8,
            "y": 0
        }
    ],
    "l4": [],
    "l5": [
        {
            "index": 0,
            "x": 12,
            "y": -2
        },
        {
            "index": 1,
            "x": 11,
            "y": -2
        },
        {
            "index": 2,
            "x": 11,
            "y": -3
        },
        {
            "index": 3,
            "x": 11,
            "y": -4
        },
        {
            "index": 4,
            "x": 11,
            "y": -5
        },
        {
            "index": 5,
            "x": 12,
            "y": -5
        },
        {
            "index": 6,
            "x": 13,
            "y": -5
        }
    ]
}